xparameter/__init__.py
xparameter/xparameter.py
xparameter-0.0.1.dist-info/licenses/LICENSE
xparameter-0.0.1.dist-info/METADATA
xparameter-0.0.1.dist-info/WHEEL
xparameter-0.0.1.dist-info/top_level.txt
xparameter-0.0.1.dist-info/RECORD
