Metadata-Version: 2.4
Name: xparameter
Version: 0.0.1
Summary: A portable configuration tool to manage hyperparameters and settings of your experiments.
Home-page: https://github.com/ThomasAtlantis/xparameter
Author: Shangyu Liu
Author-email: liushangyu@sjtu.edu.cn
Classifier: Programming Language :: Python :: 3
Classifier: License :: OSI Approved :: MIT License
Classifier: Operating System :: OS Independent
Requires-Python: >=3.7
License-File: LICENSE
Requires-Dist: rich-argparse>=1.7.0
Dynamic: author
Dynamic: author-email
Dynamic: classifier
Dynamic: description
Dynamic: description-content-type
Dynamic: home-page
Dynamic: license-file
Dynamic: requires-dist
Dynamic: requires-python
Dynamic: summary
